recuero/__init__.py
recuero/courses.py
recuero/utils.py
recuero-1.0.dist-info/METADATA
recuero-1.0.dist-info/WHEEL
recuero-1.0.dist-info/top_level.txt
recuero-1.0.dist-info/RECORD
